<annotation>
	<folder>train</folder>
	<filename>20240413_195627.jpg</filename>
	<path>C:\Users\brian\OneDrive\Desktop\hardhacks\solanaceae\solanaceae\obj_det models\train\20240413_195627.jpg</path>
	<source>
		<database>Unknown</database>
	</source>
	<size>
		<width>3024</width>
		<height>4032</height>
		<depth>3</depth>
	</size>
	<segmented>0</segmented>
	<object>
		<name>phone</name>
		<pose>Unspecified</pose>
		<truncated>0</truncated>
		<difficult>0</difficult>
		<bndbox>
			<xmin>1357</xmin>
			<ymin>1367</ymin>
			<xmax>2866</xmax>
			<ymax>2246</ymax>
		</bndbox>
	</object>
	<object>
		<name>ruler</name>
		<pose>Unspecified</pose>
		<truncated>0</truncated>
		<difficult>0</difficult>
		<bndbox>
			<xmin>96</xmin>
			<ymin>2224</ymin>
			<xmax>1435</xmax>
			<ymax>3424</ymax>
		</bndbox>
	</object>
</annotation>
